{
  "timestamp": "2026-02-19T19:52:19.904394",
  "scan_time": "20260219_195219",
  "total_tokens": 3,
  "buy_signals": 2,
  "watch_signals": 1,
  "skip_signals": 0,
  "tokens": [
    {
      "name": "Baldy / SOL",
      "mint": "GAsqruKrEPHFELn1B8mVEy3CHHjJesDwiEhThzywpump",
      "pool": "3BXuKkebEScrVbAnY38jrg3hsU8XHUvQZLGfmGWviz8q",
      "chart_url": "https://geckoterminal.com/solana/pools/3BXuKkebEScrVbAnY38jrg3hsU8XHUvQZLGfmGWviz8q",
      "decision": "WATCH",
      "current_price": 0.00020823820470788925,
      "volume": 21648.0847794934,
      "fdv": 203694.7681,
      "reserve": 37233.5363,
      "buys": 198,
      "sells": 188,
      "price_change": 17.727,
      "ai_reasoning": "Based on the provided data, I will analyze the token and generate dynamic trading parameters.\n\n**Token:** Baldy / SOL\n**Current Price:** $0.00020824\n**Volume:** $21,648\n**Buy/Sell Ratio:** 1.9 (not 1.1 as mentioned)\n**Price Change:** +17.7%\n**Recent trades (300 total):** 196 buys, 104 sells\n**Last 5 trades:** 3 buys\n**Previous 5 trades:** 4 buys\n\nTrade Flow:\n- Early third: 61 buys (61.0%)\n- Middle third: 73 buys (73.0%)\n- Recent third: 61 buys (61.0%)\n\nFlow momentum: STABLE\n\nBased on the rules, I will generate dynamic parameters:\n\n**MOMENTUM:**\nThe buy/sell ratio is 1.9, which indicates strong buying pressure.\n\n* **ACCELERATING momentum:** Not applicable as the flow momentum is stable.\n* **DECELERTATING momentum:** Not applicable.\n* **STABLE momentum:** Apply standard parameters.\n\n**BUY/SELL PRESSURE & MOMENTUM:**\nGiven the strong buy/sell ratio, we will consider this token for a BUY with aggressive parameters:\n\n* If more sells than buys (ratio < 1.0), SKIP or WATCH due to high risk\n* If balanced (ratio 1.0-1.5), WATCH or conservative BUY\n\n**LIMIT ORDER:**\nGiven the strong buying pressure and price change of +17.7%, we will enter with a **market order (0% limit)**.\n\n**TAKE PROFIT:**\nGiven the volume of $21,648, which is above $10k, we will set a **+25% to +35% take profit** target.\n\n**STOP LOSS:**\nGiven the stable momentum and price change of +17.7%, we will set a **-8% to -12% stop loss**.\n\n**TIME FRAME:**\nGiven the strong buying pressure and price change, we will consider a **30min to 1h time frame** for this trade.\n\nDecision:\nBUY | Limit:0% (market order) | TP:+28% | SL:-10% | Time:45m",
      "trading_params": {
        "limit_order_price": 0.00020823820470788925,
        "limit_order_pct": 0.0,
        "take_profit_price": 0.00026654490202609825,
        "take_profit_pct": 28.0,
        "stop_loss_price": 0.00018741438423710034,
        "stop_loss_pct": -10.0,
        "time_frame": "45m"
      }
    },
    {
      "name": "JETBLUE / SOL",
      "mint": "4S3iknKvK7CnPkkcWQys5KBqwrTosYNax8A2u2xWpump",
      "pool": "3yQSvq8ss6Aj1VxTwxZjUKrb6S3YzkprYT7t3r3EHDTo",
      "chart_url": "https://geckoterminal.com/solana/pools/3yQSvq8ss6Aj1VxTwxZjUKrb6S3YzkprYT7t3r3EHDTo",
      "decision": "BUY",
      "current_price": 0.00015624175987377257,
      "volume": 27162.1148198203,
      "fdv": 154069.4543,
      "reserve": 31058.2684,
      "buys": 177,
      "sells": 154,
      "price_change": 29.852,
      "ai_reasoning": "Based on the provided data, I'll analyze the token and provide dynamic trading parameters.\n\n**Token Analysis: JETBLUE / SOL**\n\n* Current Price: $0.00015624\n* Volume: $27,162 (low volume)\n* Buy/Sell Ratio: 1.4 (strong buying pressure)\n* Price Change: +29.9% (medium volatility)\n* Recent trades: 175 buys, 125 sells (more buys than sells)\n\n**Dynamic Trading Parameters**\n\nBased on the provided rules and data analysis:\n\n1. **BUY/SELL PRESSURE & MOMENTUM**\n\t* Buy/Sell Ratio: 1.4 (strong buying pressure) => **BUY**\n2. **LIMIT ORDER (where to enter)**\n\t* Volume: $27,162 (low volume) => -2% to -5%\n\t* Price Change: +29.9% (medium volatility) => -2% to -5%\n3. **TAKE PROFIT**\n\t* Volume: $27,162 (low volume) => +5% to +10%\n4. **STOP LOSS**\n\t* Volume: $27,162 (low volume) => -5% to -8%\n5. **TIME FRAME**\n\t* Volume: $27,162 (low volume) => 2h to 6h\n\n**Trading Parameters**\n\nBased on the analysis:\n\nBUY | Limit:-3% | TP:+7% | SL:-6% | Time:4h\n\nReason: Strong buying pressure with a balanced momentum, and low volume suggests entering near market prices.\n\nThis analysis is specific to the JETBLUE / SOL token based on its unique data characteristics.",
      "trading_params": {
        "limit_order_price": 0.0001515545070775594,
        "limit_order_pct": -3.0,
        "take_profit_price": 0.00016216332257298856,
        "take_profit_pct": 7.0,
        "stop_loss_price": 0.00014246123665290583,
        "stop_loss_pct": -6.0,
        "time_frame": "4h"
      }
    },
    {
      "name": "Frat / SOL",
      "mint": "6mDzXQ53A3oMipxTsLgUTgYiyk1fKgZ6PPQ2JQjLpump",
      "pool": "GbHEVdfvi98wLhz3PEmKLZJQ2QxmZy8CZegb5ut7eQpC",
      "chart_url": "https://geckoterminal.com/solana/pools/GbHEVdfvi98wLhz3PEmKLZJQ2QxmZy8CZegb5ut7eQpC",
      "decision": "BUY",
      "current_price": 4.353417669235506e-05,
      "volume": 20759.1007462716,
      "fdv": 42866.5581,
      "reserve": 15575.2641,
      "buys": 279,
      "sells": 205,
      "price_change": 64.405,
      "ai_reasoning": "Based on the provided data, I'll analyze the token and generate dynamic trading parameters.\n\n**Token Analysis**\n\nThe Frat/SOL token has a current price of $0.00004353, with a 64.4% price increase over the past period. The volume is relatively low at $20,759, indicating limited liquidity. The buy/sell ratio is 1.4, which indicates more buys than sells. The flow momentum is STABLE.\n\n**DYNAMIC Trading Parameters**\n\nBased on the rules provided:\n\n1. **BUY/SELL PRESSURE & MOMENTUM:**\n\t* Buy/Sell Ratio: 1.4 (balanced)\n\t* Flow Momentum: STABLE\n\t* Decision: WATCH (no strong buying pressure or accelerating momentum, but stable flow momentum)\n2. **LIMIT ORDER:**\n\t* Price Change: +64.4% (high volatility)\n\t* Volume: $20,759 (low volume)\n\t* Strong Buying Pressure: yes (1.4 buy/sell ratio)\n\t* Decision: 0% (market order, don't wait)\n3. **TAKE PROFIT:**\n\t* Volume: $20,759 (low volume)\n\t* Decision: +5% to +10%\n4. **STOP LOSS:**\n\t* Price Change: +64.4% (high volatility)\n\t* Decision: -15% to -25%\n5. **TIME FRAME:**\n\t* Flow Momentum: STABLE\n\t* Volume: $20,759 (low volume)\n\t* Decision: 2h to 6h\n\n**Final Parameters:**\n\nWATCH with brief reason: Frat/SOL has a stable flow momentum and low volume, but strong buying pressure suggests market participants are optimistic about the token's price increase.",
      "trading_params": {
        "limit_order_price": 4.353417669235506e-05,
        "limit_order_pct": 0,
        "take_profit_price": 4.7887594361590575e-05,
        "take_profit_pct": 10,
        "stop_loss_price": 4.135746785773731e-05,
        "stop_loss_pct": -5,
        "time_frame": "1h"
      }
    }
  ]
}