{
  "timestamp": "2026-02-26T11:22:04.659684",
  "scan_time": "20260226_112204",
  "total_tokens": 3,
  "buy_signals": 3,
  "watch_signals": 0,
  "skip_signals": 0,
  "tokens": [
    {
      "name": "woofinator / SOL",
      "mint": "FdiKGJmxAr8kextLpGtJVqAJvU7hic9E8RAFKo7Kpump",
      "pool": "CzgPcAUhh5jqsmHkV3zc4Laoww8DipWRcwno4fgwn3L8",
      "chart_url": "https://geckoterminal.com/solana/pools/CzgPcAUhh5jqsmHkV3zc4Laoww8DipWRcwno4fgwn3L8",
      "decision": "BUY",
      "current_price": 1.0690026402156023e-05,
      "volume": 1397.7930939266,
      "fdv": 10101.91202,
      "reserve": 5155.6803,
      "buys": 23,
      "sells": 20,
      "price_change": 8.438,
      "ai_reasoning": "Based on the provided data and dynamic trading parameters, I will analyze the Solana token \"woofinator\" and provide a trading decision.\n\n**Buy/Sell Ratio:** 1.1 ( slightly above balanced)\n**Flow Momentum:** STABLE\n**Recent trades:** No recent buys or sells in the last 5 trades, indicating a possible market pause.\n**Price Change:** +8.4% ( moderate volatility)\n\nGiven these parameters:\n\n1. **BUY/SELL PRESSURE & MOMENTUM:**\nSince the buy/sell ratio is slightly above balanced (1.0-1.5), and flow momentum is stable, we can consider a conservative BUY.\n\n2. **LIMIT ORDER:**\nConsidering the moderate price change (+8.4%) and the fact that there are no recent trades, we'll enter near market with a slight negative limit to ensure we get in at a good price.\n**Limit:** -1%\n\n3. **TAKE PROFIT:**\nGiven the moderate volume ($1,398) and stable momentum, we can aim for a standard take profit range.\n**TP:** +10% to +15% (targeting $0.00001204 to $0.00001302)\n\n4. **STOP LOSS:**\nWith moderate volatility and stable momentum, we'll set a stop loss that allows some room for price fluctuations.\n**SL:** -6% to -8% ($0.00001069 - $0.00001124)\n\n5. **TIME FRAME:**\nConsidering the market conditions are relatively calm, we can use a slightly longer time frame to allow more liquidity and better exit opportunities.\n**Time:** 4h\n\nDecision:\nBUY | Limit:-1% | TP:+12% | SL:-7% | Time:4h",
      "trading_params": {
        "limit_order_price": 1.0583126138134462e-05,
        "limit_order_pct": -1.0,
        "take_profit_price": 1.1853101274710597e-05,
        "take_profit_pct": 12.0,
        "stop_loss_price": 9.842307308465049e-06,
        "stop_loss_pct": -7.0,
        "time_frame": "4h"
      }
    },
    {
      "name": "CORNER / SOL",
      "mint": "9mfKc66yLkNpfBKfAGXUZBe3AyZetoP8tVFofXbfpump",
      "pool": "86groPW2edeTJWpbnAdXtPHmqAM5Qfr1HNXbQpresTWi",
      "chart_url": "https://geckoterminal.com/solana/pools/86groPW2edeTJWpbnAdXtPHmqAM5Qfr1HNXbQpresTWi",
      "decision": "BUY",
      "current_price": 0.0002462574120196912,
      "volume": 1445.1606623508,
      "fdv": 246257.412,
      "reserve": 48128.8508,
      "buys": 27,
      "sells": 10,
      "price_change": 0.14,
      "ai_reasoning": "Based on the provided data, I'll apply the dynamic trading parameters to determine a trade decision for CORNER token.\n\n**Buy/Sell Pressure & Momentum:**\nThe buy/sell ratio is 2.7, indicating strong buying pressure. There are more buys than sells in recent trades (142 vs 158) and even in the last 5 trades (3 buys). However, there's also a stable momentum flow with no significant acceleration or deceleration.\n\n**Decision:** BUY\n\n**Limit Order:**\nSince there's strong buying pressure, we can enter near market price. With low volatility (<10%), we'll aim for a small dip of -2%.\n\n**TAKE PROFIT (TP):**\nWith medium volume ($1,445), the TP will be set at +10% to +20%. Given the stable momentum and low volatility, let's aim for the lower end of this range.\n\n**STOP LOSS (SL):**\nConsidering low volatility and stable momentum, we'll set a conservative SL at -5%.\n\n**TIME FRAME:**\nWith strong buying pressure and low volume, we can expect a trend to develop. Let's use a 4h time frame to capture potential price movements.\n\n**Final Decision:**\nBUY | Limit:-2% | TP:+10% | SL:-5% | Time:4h\n\nNote that this decision is based on the specific data provided and may not be suitable for all market conditions or future developments.",
      "trading_params": {
        "limit_order_price": 0.00024133226377929737,
        "limit_order_pct": -2.0,
        "take_profit_price": 0.00026546549015722714,
        "take_profit_pct": 10.0,
        "stop_loss_price": 0.00022926565059033248,
        "stop_loss_pct": -5.0,
        "time_frame": "4h"
      }
    },
    {
      "name": "Axioom / SOL",
      "mint": "BHCdQCumiLKfgMoPh3krxCGqo8YBwizo21wH2yZQpump",
      "pool": "4LzRHKrda1AEAXSxEi9UH4neYJZQZZ5Z7MfRhPnupVqu",
      "chart_url": "https://geckoterminal.com/solana/pools/4LzRHKrda1AEAXSxEi9UH4neYJZQZZ5Z7MfRhPnupVqu",
      "decision": "BUY",
      "current_price": 2.7513551943334735e-05,
      "volume": 794.9422789805,
      "fdv": 27513.55194,
      "reserve": 13346.2598,
      "buys": 9,
      "sells": 11,
      "price_change": -4.255,
      "ai_reasoning": "Based on the provided data, I will analyze the token and output dynamic trading parameters.\n\n**Token Analysis: Axioom / SOL**\n\n* Current Price: $0.00002751\n* Volume: $795 (low volume)\n* Buy/Sell Ratio: 1.155 (slightly above balance, indicating strong buying pressure)\n* Price Change: -4.3% (medium volatility)\n* Recent trades: 161 buys, 139 sells (strong buying pressure)\n\n**Dynamic Trading Parameters**\n\n1. **BUY/SELL PRESSURE & MOMENTUM**\n\t* Buy/Sell Ratio: 1.155 (slightly above balance) -> Strong buying pressure\n\t* Momentum: STABLE (no acceleration or deceleration)\n\t* Recommendation: BUY with aggressive parameters\n\n2. **LIMIT ORDER (where to enter)**\n\t* Volume: Low ($795) -> Enter near market (-0% to -1%)\n\t* Price Change: Medium volatility (-4.3%) -> Wait for a bigger dip (-5% limit)\n\n3. **TAKE PROFIT**\n\t* Volume: Low ($795) -> Take profit early (+5% to +10%)\n\n4. **STOP LOSS**\n\t* Price Change: Medium volatility (-4.3%) -> Room to breathe (-8% to -12%)\n\n5. **TIME FRAME**\n\t* Volume: Low ($795) -> Trade within 2h to 6h ( standard parameters)\n\n**Trading Decision**\n\nBUY | Limit:-1% | TP:+7% | SL:-10% | Time:4h\n\nThe token shows strong buying pressure with a balanced momentum, indicating a potential long-term trend. With low volume and medium volatility, we can enter near the market price (-1%) and set a take profit at +7%. A stop loss of -10% will provide sufficient room to breathe in case the trade doesn't go as expected. Trading within 4h to 6h should allow for timely adjustments if needed.\n\nPlease note that these parameters are dynamic and may change based on further data analysis or market developments.",
      "trading_params": {
        "limit_order_price": 2.7238416423901386e-05,
        "limit_order_pct": -1.0,
        "take_profit_price": 2.9145105573574486e-05,
        "take_profit_pct": 7.0,
        "stop_loss_price": 2.451457478151125e-05,
        "stop_loss_pct": -10.0,
        "time_frame": "4h"
      }
    }
  ]
}