{
  "timestamp": "2026-02-01T14:43:00.265824",
  "scan_time": "20260201_144300",
  "total_tokens": 3,
  "buy_signals": 3,
  "watch_signals": 0,
  "skip_signals": 0,
  "tokens": [
    {
      "name": "Pussy / SOL",
      "mint": "6mJ4m8vmjLbpVMjeQ4G8mYfCLzkUWSEnVEmuMjB7pump",
      "pool": "8TLhauhM7GDkekCxqUwqjPLg9DScWz1YP43UVHHpYW39",
      "chart_url": "https://geckoterminal.com/solana/pools/8TLhauhM7GDkekCxqUwqjPLg9DScWz1YP43UVHHpYW39",
      "decision": "BUY",
      "current_price": 8.268144933149557e-05,
      "volume": 47610.646905264,
      "fdv": 86269.03796,
      "reserve": 25289.8824,
      "buys": 997,
      "sells": 452,
      "price_change": 31.637,
      "ai_reasoning": "BUY | Limit:0% | TP:+15% | SL:-8% | Time:4h",
      "trading_params": {
        "limit_order_price": 8.268144933149557e-05,
        "limit_order_pct": 0.0,
        "take_profit_price": 9.50836667312199e-05,
        "take_profit_pct": 15.0,
        "stop_loss_price": 7.606693338497593e-05,
        "stop_loss_pct": -8.0,
        "time_frame": "4h"
      }
    },
    {
      "name": "\u04fe / SOL",
      "mint": "C7QbKjpC3WEHCqRbZBosjk93Ci3sU4w2XRc5YGKPpump",
      "pool": "CvSxLMxXbe2pbiAMMRCcSp5TLFcF97pshuSX9DdE1oAe",
      "chart_url": "https://geckoterminal.com/solana/pools/CvSxLMxXbe2pbiAMMRCcSp5TLFcF97pshuSX9DdE1oAe",
      "decision": "BUY",
      "current_price": 0.0002256370780366205,
      "volume": 30116.7937951687,
      "fdv": 234649.0245,
      "reserve": 42726.8316,
      "buys": 215,
      "sells": 182,
      "price_change": 24.654,
      "ai_reasoning": "**Rationale:**  \n- **Buy/Sell Pressure:** Ratio of 1.2 (balanced) with strong recent buy flow (164 buys vs. 136 sells) and stable momentum suggests a conservative buy.  \n- **Limit Order:** Medium volatility (24.7% price change) \u2192 -3% (mid-range of -2% to -5%).  \n- **Take Profit:** Medium volume ($30k) \u2192 +15% (mid-range of +10% to +20%).  \n- **Stop Loss:** Medium volatility \u2192 -10% (mid-range of -8% to -15%).  \n- **Time Frame:** Stable momentum with a strong price surge (24.7%) \u2192 4h (balances trend-following and risk management).",
      "trading_params": {
        "limit_order_price": 0.0002188679656955219,
        "limit_order_pct": -3.0,
        "take_profit_price": 0.0002516981605498502,
        "take_profit_pct": 15.0,
        "stop_loss_price": 0.0001969811691259697,
        "stop_loss_pct": -10.0,
        "time_frame": "4h"
      }
    },
    {
      "name": "10/10 / SOL",
      "mint": "Hvkze6p1JSW7svxb1V5nFni4Sc2BifL48VVT6uB7pump",
      "pool": "r7hhh1i4XJ1eKtVvpMaZK89ZiLnpHxZx2yT6uWiekdG",
      "chart_url": "https://geckoterminal.com/solana/pools/r7hhh1i4XJ1eKtVvpMaZK89ZiLnpHxZx2yT6uWiekdG",
      "decision": "BUY",
      "current_price": 9.464588253968548e-05,
      "volume": 16957.4845286327,
      "fdv": 94844.10784,
      "reserve": 27031.3978,
      "buys": 179,
      "sells": 152,
      "price_change": 21.664,
      "ai_reasoning": "**Decision:** WATCH  \n**Reasoning:** The buy/sell ratio of 1.2 indicates a balanced market, falling within the 1.0\u20131.5 range. While recent trades and flow show strong buying pressure, the ratio itself does not meet the threshold for aggressive buying. Stable momentum suggests caution, aligning with a \"WATCH\" decision rather than immediate action.  \n\n**Parameters:**  \n- **Limit Order:** -2% to -5% (medium volatility)  \n- **Take Profit:** +10% to +20% (medium volume)  \n- **Stop Loss:** -8% to -15% (medium volatility)  \n- **Time Frame:** 2h to 6h (standard for balanced momentum)  \n\n**Final Output:**  \n**WATCH**  \n*Balanced buy/sell ratio with stable momentum, but not strong enough for aggressive buy.*",
      "trading_params": {
        "limit_order_price": 9.464588253968548e-05,
        "limit_order_pct": 0,
        "take_profit_price": 0.00010411047079365404,
        "take_profit_pct": 10,
        "stop_loss_price": 8.99135884127012e-05,
        "stop_loss_pct": -5,
        "time_frame": "1h"
      }
    }
  ]
}