{
  "timestamp": "2026-02-26T04:32:44.461450",
  "scan_time": "20260226_043244",
  "total_tokens": 3,
  "buy_signals": 3,
  "watch_signals": 0,
  "skip_signals": 0,
  "tokens": [
    {
      "name": "ESSENCE / SOL",
      "mint": "6nDUuWpdTGiom4BRXtLMtWyT9UfNuKFLo86MYPGgpump",
      "pool": "CiFnAVsGjEfLiGfYSPG7um7Ef5LDzbYsW9DhLG9sMR8w",
      "chart_url": "https://geckoterminal.com/solana/pools/CiFnAVsGjEfLiGfYSPG7um7Ef5LDzbYsW9DhLG9sMR8w",
      "decision": "BUY",
      "current_price": 0.00015858259605026957,
      "volume": 24590.074894131,
      "fdv": 156464.7316,
      "reserve": 32182.639,
      "buys": 219,
      "sells": 163,
      "price_change": -11.979,
      "ai_reasoning": "Based on the provided data, I'll apply the dynamic trading parameters to determine the decision for ESSENCE/SOL.\n\n**BUY/SELL PRESSURE & MOMENTUM:**\nThe buy/sell ratio is 1.3, indicating a balanced market. However, considering the recent trades (last 5 trades: 2 buys), there's some evidence of buying momentum. The flow momentum is STABLE, which suggests that we should adopt standard parameters.\n\n**LIMIT ORDER:**\nGiven the low volatility (< 10%) and stable momentum, I'll choose an entry point near the market. With strong buying pressure, it's optimal to use a market order (0%).\n\n**TAKE PROFIT:**\nThe volume is $24,590, which falls between medium ($3k-$10k) and high (> $10k). As such, I'll select the upper bound of the range for take profit: +20%.\n\n**STOP LOSS:**\nConsidering low volatility (< 10%), a relatively tight stop loss is suitable. However, given the recent price change (-12.0%), we should also account for some room to breathe.\n\n**TIME FRAME:**\nWith stable momentum and low volume, I'll choose a moderate time frame of 2h to allow for some market movement without being overly aggressive.\n\n**Decision:**\nGiven these parameters, I'll provide a BUY signal with dynamic values:\n\nBUY | Limit:0% | TP:+20% | SL:-8% | Time:2h\n\nThe reasoning behind this decision is that there's balanced buying pressure and stable momentum, which indicates a relatively safe entry point near the market. The take profit level is set to +20% due to moderate volume, and the stop loss is -8% to account for some room to breathe in low-volatility conditions.",
      "trading_params": {
        "limit_order_price": 0.00015858259605026957,
        "limit_order_pct": 0.0,
        "take_profit_price": 0.00019029911526032348,
        "take_profit_pct": 20.0,
        "stop_loss_price": 0.000145895988366248,
        "stop_loss_pct": -8.0,
        "time_frame": "2h"
      }
    },
    {
      "name": "PRESSED / SOL",
      "mint": "7Yi9d249xnY1i9QpcANN3a5pfkkhZt2T471Tyfqjpump",
      "pool": "CRTMk9Yy5P2nuUjko7YUGCnhLo8W7pj2uFkFyFrAZ89W",
      "chart_url": "https://geckoterminal.com/solana/pools/CRTMk9Yy5P2nuUjko7YUGCnhLo8W7pj2uFkFyFrAZ89W",
      "decision": "BUY",
      "current_price": 4.002978165770246e-05,
      "volume": 3756.2772674121,
      "fdv": 40283.0564,
      "reserve": 15952.1551,
      "buys": 43,
      "sells": 46,
      "price_change": 5.026,
      "ai_reasoning": "Based on the provided data, I will analyze each parameter dynamically and make a decision.\n\n1. **BUY/SELL PRESSURE & MOMENTUM**:\n\nThe buy/sell ratio is 0.9, indicating more sells than buys. However, the flow momentum is STABLE, which suggests that the buying pressure is accelerating.\n\nSince there are more sells than buys, I will be cautious and set parameters to standard levels for now. Given the stable momentum, we can expect some volatility in the short term.\n\n* Aggressive entry: NO\n* Standard parameters:\n\t+ Buy/Sell Ratio: 0.9 (more sells)\n\t+ Flow Momentum: STABLE\n\n2. **LIMIT ORDER (where to enter)**:\n\nThe price change is +5.0%, which indicates low volatility (< 10%). Given the stable momentum, we can consider entering near the market.\n\n* Limit Order:\n\t+ Low Volatility: Enter near market\n\t+ Price Change: +5.0%",
      "trading_params": {
        "limit_order_price": 4.002978165770246e-05,
        "limit_order_pct": 0,
        "take_profit_price": 4.403275982347271e-05,
        "take_profit_pct": 10,
        "stop_loss_price": 3.8028292574817335e-05,
        "stop_loss_pct": -5,
        "time_frame": "1h"
      }
    },
    {
      "name": "CORNER / SOL",
      "mint": "9mfKc66yLkNpfBKfAGXUZBe3AyZetoP8tVFofXbfpump",
      "pool": "86groPW2edeTJWpbnAdXtPHmqAM5Qfr1HNXbQpresTWi",
      "chart_url": "https://geckoterminal.com/solana/pools/86groPW2edeTJWpbnAdXtPHmqAM5Qfr1HNXbQpresTWi",
      "decision": "BUY",
      "current_price": 8.384230456620634e-05,
      "volume": 10119.5365196753,
      "fdv": 84708.84065,
      "reserve": 28342.778,
      "buys": 109,
      "sells": 73,
      "price_change": 9.014,
      "ai_reasoning": "Based on the provided data, I will analyze the Solana token CORNER and provide dynamic trading parameters.\n\n**Token Analysis:**\n\n* Current Price: $0.00008384\n* Volume: $10,120\n* Buy/Sell Ratio: 1.5 (strong buying pressure)\n* Recent trades: 4 buys in last 5 trades, indicating accelerating momentum\n* Trade Flow:\n\t+ Early third (100 trades): 56 buys (56.0%)\n\t+ Middle third (100 trades): 60 buys (60.0%)\n\t+ Recent third (100 trades): 56 buys (56.0%), showing stable momentum\n\n**Decision:**\n\nGiven the strong buying pressure, accelerating momentum, and high volume, I recommend a **BUY** with aggressive parameters.\n\n**Trade Parameters:**\n\n* Limit: -0% (market order, don't wait)\n* TP: +20% to +30% (more liquidity to exit due to high volume)\n* SL: -8% to -12% (room to breathe for aggressive entry)\n\n**Time Frame:** 1h to 2h (quick trade with strong trend)\n\n**Format:**\n\nBUY | Limit:-0% | TP:+25% | SL:-10% | Time:1.5h\n\nThis decision is based on the following reasoning:\n\n* Strong buying pressure indicates a potential uptrend.\n* Accelerating momentum suggests that the price will continue to rise.\n* High volume provides liquidity for exit and reduces the risk of stop-loss being hit.\n* Aggressive entry parameters (TP +25%, SL -10%) are justified due to the high volume and accelerating momentum.\n\nNote: As this is a new token with limited trading history, it's essential to monitor the market closely and adjust parameters as needed.",
      "trading_params": {
        "limit_order_price": 8.384230456620634e-05,
        "limit_order_pct": -0.0,
        "take_profit_price": 0.0001006107654794476,
        "take_profit_pct": 20.0,
        "stop_loss_price": 7.713492020090983e-05,
        "stop_loss_pct": -8.0,
        "time_frame": "1.5h"
      }
    }
  ]
}