{
  "timestamp": "2026-02-12T23:36:44.479680",
  "scan_time": "20260212_233644",
  "total_tokens": 3,
  "buy_signals": 3,
  "watch_signals": 0,
  "skip_signals": 0,
  "tokens": [
    {
      "name": "Rohun / SOL",
      "mint": "7qMManxJoj8nLUvRwgQe3D9KZf6iCvVLcv7Vm5Hkpump",
      "pool": "DMHy8CveFZPtALuST9PUGSqgX9Lz7L4oWusXYFnxRwPo",
      "chart_url": "https://geckoterminal.com/solana/pools/DMHy8CveFZPtALuST9PUGSqgX9Lz7L4oWusXYFnxRwPo",
      "decision": "BUY",
      "current_price": 2.0356273117124053e-05,
      "volume": 5879.7382509178,
      "fdv": 19316.09733,
      "reserve": 10522.4373,
      "buys": 93,
      "sells": 71,
      "price_change": 24.623,
      "ai_reasoning": "BUY | Limit:-3% | TP:+15% | SL:-10% | Time:6h",
      "trading_params": {
        "limit_order_price": 1.9745584923610332e-05,
        "limit_order_pct": -3.0,
        "take_profit_price": 2.270742266215188e-05,
        "take_profit_pct": 15.0,
        "stop_loss_price": 1.77710264312493e-05,
        "stop_loss_pct": -10.0,
        "time_frame": "6h"
      }
    },
    {
      "name": "PCRAB / SOL",
      "mint": "2CCx3i6z3e3mqXvM26viQd7KZ1QzqpAh3MWHu1abpump",
      "pool": "67CBm58ekzbCssb6gtNNn45Gn57pHS5ftr8RUiSprAwq",
      "chart_url": "https://geckoterminal.com/solana/pools/67CBm58ekzbCssb6gtNNn45Gn57pHS5ftr8RUiSprAwq",
      "decision": "BUY",
      "current_price": 3.390346212611568e-05,
      "volume": 4891.2037699652,
      "fdv": 31342.07094,
      "reserve": 13044.5663,
      "buys": 81,
      "sells": 47,
      "price_change": 13.019,
      "ai_reasoning": "BUY | Limit:0% | TP:+15% | SL:-10% | Time:2h to 6h",
      "trading_params": {
        "limit_order_price": 3.390346212611568e-05,
        "limit_order_pct": 0.0,
        "take_profit_price": 3.8988981445033025e-05,
        "take_profit_pct": 15.0,
        "stop_loss_price": 3.051311591350411e-05,
        "stop_loss_pct": -10.0,
        "time_frame": "2h"
      }
    },
    {
      "name": "KOLPEDIA / SOL",
      "mint": "CBidr36KQsWJMAtgsU8z192oMDE9jb8PMTePiLmYpump",
      "pool": "FoigeUEMitGNPzsVYPnvL4mEnyVFAeogzB4RX9vKgWTS",
      "chart_url": "https://geckoterminal.com/solana/pools/FoigeUEMitGNPzsVYPnvL4mEnyVFAeogzB4RX9vKgWTS",
      "decision": "BUY",
      "current_price": 1.999823920266107e-05,
      "volume": 2144.0232298488,
      "fdv": 20218.56873,
      "reserve": 10604.2886,
      "buys": 32,
      "sells": 33,
      "price_change": 8.93,
      "ai_reasoning": "**Reasoning:**  \n- **Buy/Sell Ratio (1.0):** Balanced, but recent trades (168 buys, 132 sells) and flow momentum (stable) suggest **conservative buying pressure**.  \n- **Volatility (8.9% price change):** Medium, so **-2% limit** (entering near market).  \n- **Volume ($2,144):** Low, so **+7% TP** (take profit early) and **-6% SL** (moderate stop loss).  \n- **Time Frame:** Medium volatility + low volume \u2192 **3h** (balance quick entry and exit).  \n- **Flow Analysis:** Recent third (55% buys) and stable momentum justify **aggressive entry** with tight TP/SL.  \n\n**Decision:** BUY with dynamic parameters tailored to medium volatility and balanced buying pressure.",
      "trading_params": {
        "limit_order_price": 1.9598274418607847e-05,
        "limit_order_pct": -2.0,
        "take_profit_price": 2.09701536279104e-05,
        "take_profit_pct": 7.0,
        "stop_loss_price": 1.8422377953491374e-05,
        "stop_loss_pct": -6.0,
        "time_frame": "3h"
      }
    }
  ]
}