{
  "timestamp": "2026-01-08T05:01:33.521609",
  "scan_time": "20260108_050133",
  "total_tokens": 8,
  "buy_signals": 8,
  "watch_signals": 0,
  "skip_signals": 0,
  "tokens": [
    {
      "name": "VIBE / SOL",
      "mint": "3HRQ9VpJgAXTLD98b3vy7u3vbKqeEKiJ12RmEghnpump",
      "pool": "4U74r1ocE46mMhNtyqpA4yPuAAKL6yNKVkRMoVWLfLmW",
      "chart_url": "https://geckoterminal.com/solana/pools/4U74r1ocE46mMhNtyqpA4yPuAAKL6yNKVkRMoVWLfLmW",
      "decision": "BUY",
      "current_price": 3.7933146728849256e-05,
      "volume": 33746.7321273694,
      "fdv": 37242.46567,
      "reserve": 10748.0704,
      "buys": 424,
      "sells": 290,
      "price_change": 99.083,
      "ai_reasoning": "**Answer:**\n\nBUY | Limit:-5% | TP:+20% | SL:-15% | Time:30min\n\n**Explanation:**\n\n1. **Decision (BUY):**  \n   - The price change of +99.1% indicates strong upward momentum.  \n   - While the overall ratio (1.5) is at the upper bound of \"balanced\" (per Rule 1), recent trades (last 5 buys, previous 5 buys) suggest **strong buying pressure**, pushing the decision toward **BUY** with **aggressive parameters**.\n\n2. **Limit Order (-5%):**  \n   - High volatility (price change >50%) requires a conservative limit order at -5% to -10% (Rule 2). Choosing -5% balances risk and reward.\n\n3. **Take Profit (+20%):**  \n   - Volume is $33,747 (> $10k), qualifying as **high volume** (Rule 3). High volume allows for a **+20% to +40%** take profit range. Choosing +20% is a balanced target.\n\n4. **Stop Loss (-15%):**  \n   - High volatility (price change >50%) mandates a **-15% to -25%** stop loss (Rule 4). -15% provides adequate protection without being overly restrictive.\n\n5. **Time Frame (30min):**  \n   - High volatility (Rule 1) suggests a **30min to 2h** time frame. 30min aligns with short-term momentum and quick profit-taking.\n\n**Final Answer:**  \nBUY | Limit:-5% | TP:+20% | SL:-15% | Time:30min",
      "trading_params": {
        "limit_order_price": 3.603648939240679e-05,
        "limit_order_pct": -5.0,
        "take_profit_price": 4.324378727088815e-05,
        "take_profit_pct": 20.0,
        "stop_loss_price": 3.063101598354577e-05,
        "stop_loss_pct": -15.0,
        "time_frame": "30min"
      }
    },
    {
      "name": "SharkWhale / SOL",
      "mint": "9bHN9R71bZDUgDuMi147DSizWmeRipJPFP6Uu2uJpump",
      "pool": "7GVMgyLSE5X9D2oSF6CyurYRhRQGse8E9obioMWBrsbj",
      "chart_url": "https://geckoterminal.com/solana/pools/7GVMgyLSE5X9D2oSF6CyurYRhRQGse8E9obioMWBrsbj",
      "decision": "BUY",
      "current_price": 0.00013877196639944987,
      "volume": 29903.0021396882,
      "fdv": 134019.1211,
      "reserve": 35873.5353,
      "buys": 173,
      "sells": 91,
      "price_change": 40.497,
      "ai_reasoning": "BUY | Limit:0% | TP:+15% | SL:-15% | Time:1h",
      "trading_params": {
        "limit_order_price": 0.00013877196639944987,
        "limit_order_pct": 0.0,
        "take_profit_price": 0.00015958776135936733,
        "take_profit_pct": 15.0,
        "stop_loss_price": 0.00011795617143953239,
        "stop_loss_pct": -15.0,
        "time_frame": "1h"
      }
    },
    {
      "name": "fish / SOL",
      "mint": "CmgJ1PobhUqB7MEa8qDkiG2TUpMTskWj8d9JeZWSpump",
      "pool": "7YW47DAivaQxHHYVRsP2eGzMcAMGx4czhdJ7XEFUMoYs",
      "chart_url": "https://geckoterminal.com/solana/pools/7YW47DAivaQxHHYVRsP2eGzMcAMGx4czhdJ7XEFUMoYs",
      "decision": "BUY",
      "current_price": 0.01074253040749749,
      "volume": 14342.6144566917,
      "fdv": 10835720.538812,
      "reserve": 456188.9337,
      "buys": 26,
      "sells": 88,
      "price_change": 2.347,
      "ai_reasoning": "WATCH (Buy/Sell Ratio <1.0 indicates high sell pressure, but recent 5 trades show 2 buys. Limit: 0% to -2% (low volatility), TP: +15% to +20% (medium volume), SL: -5% to -8% (low volatility), Time: 2h to 6h)",
      "trading_params": {
        "limit_order_price": 0.01074253040749749,
        "limit_order_pct": 0.0,
        "take_profit_price": 0.012353909968622113,
        "take_profit_pct": 15.0,
        "stop_loss_price": 0.010205403887122615,
        "stop_loss_pct": -5.0,
        "time_frame": "2h"
      }
    },
    {
      "name": "Bluefin / SOL",
      "mint": "EkfDd5QhE3WVhkynEtg6JWTea7w66r9oakhQNx4Qpump",
      "pool": "3ca1KatfwVh4xwPLJB2Z8kCKPcpKWJ4E7HGJsRdtV819",
      "chart_url": "https://geckoterminal.com/solana/pools/3ca1KatfwVh4xwPLJB2Z8kCKPcpKWJ4E7HGJsRdtV819",
      "decision": "BUY",
      "current_price": 0.0024047888944515464,
      "volume": 16576.1870326661,
      "fdv": 2480266.953,
      "reserve": 158989.4182,
      "buys": 98,
      "sells": 77,
      "price_change": 1.491,
      "ai_reasoning": "**Rationale:**  \n- **BUY Signal:** Buy/Sell Ratio (1.3) indicates balanced pressure, but recent trades (172 buys vs. 128 sells) and strong flow momentum (60% buys in all thirds) suggest strong underlying buying interest.  \n- **Limit Order:** Low volatility (1.5% price change) + strong buying pressure (recent trades) = **0% (market order)** to avoid waiting for dips.  \n- **Take Profit:** Medium volume ($16.5k) = **+15%** (mid-range of +10%\u2013+20%).  \n- **Stop Loss:** Low volatility = **-6%** (mid-range of -5%\u2013-8%).  \n- **Time Frame:** Stable momentum + medium volume = **2h\u20136h** for balanced risk/reward.",
      "trading_params": {
        "limit_order_price": 0.0024047888944515464,
        "limit_order_pct": 0.0,
        "take_profit_price": 0.002765507228619278,
        "take_profit_pct": 15.0,
        "stop_loss_price": 0.0022605015607844534,
        "stop_loss_pct": -6.0,
        "time_frame": "2h"
      }
    },
    {
      "name": "89 / SOL",
      "mint": "89E7wc1H2LmzEGSa96hWURcsVs5V9ByWdNM7rctSpump",
      "pool": "6vgrGqG3p3NXrPazKPFDon15HLWL5pMRSQYgZvmDC88Q",
      "chart_url": "https://geckoterminal.com/solana/pools/6vgrGqG3p3NXrPazKPFDon15HLWL5pMRSQYgZvmDC88Q",
      "decision": "BUY",
      "current_price": 0.00027267426715679943,
      "volume": 1218.808150146,
      "fdv": 258536.6924,
      "reserve": 51391.388,
      "buys": 7,
      "sells": 4,
      "price_change": 4.899,
      "ai_reasoning": "BUY | Limit:0% | TP:+10% | SL:-8% | Time:4h",
      "trading_params": {
        "limit_order_price": 0.00027267426715679943,
        "limit_order_pct": 0.0,
        "take_profit_price": 0.0002999416938724794,
        "take_profit_pct": 10.0,
        "stop_loss_price": 0.00025086032578425547,
        "stop_loss_pct": -8.0,
        "time_frame": "4h"
      }
    },
    {
      "name": "Ren\u00e9e / SOL",
      "mint": "3iWneHEeSaAe3tMBp45B4fMFQWbrYWLLitRa6P84pump",
      "pool": "3wBynFWhPpGezAbf6fFji9GqNBU1BYeAtSKtjscyhoNb",
      "chart_url": "https://geckoterminal.com/solana/pools/3wBynFWhPpGezAbf6fFji9GqNBU1BYeAtSKtjscyhoNb",
      "decision": "BUY",
      "current_price": 9.407500743539937e-05,
      "volume": 1940.1310540938,
      "fdv": 93050.20992,
      "reserve": 32202.6721,
      "buys": 11,
      "sells": 13,
      "price_change": 7.625,
      "ai_reasoning": "WATCH (Buy/Sell Ratio <1.0 indicates high risk, but stable flow momentum suggests caution)  \nLimit:-3% | TP:+7% | SL:-6.5% | Time:4h",
      "trading_params": {
        "limit_order_price": 9.125275721233739e-05,
        "limit_order_pct": -3.0,
        "take_profit_price": 9.764045021720101e-05,
        "take_profit_pct": 7.0,
        "stop_loss_price": 8.532132799353547e-05,
        "stop_loss_pct": -6.5,
        "time_frame": "4h"
      }
    },
    {
      "name": "MUSH / SOL",
      "mint": "CQ4PZEmJkR8Zchhfp21fkoCAJuZiv2dhA4QfKqupump",
      "pool": "24MzcN75D8BZSd5ZmCncSyMhe9unagiubwPNgLyaZWuX",
      "chart_url": "https://geckoterminal.com/solana/pools/24MzcN75D8BZSd5ZmCncSyMhe9unagiubwPNgLyaZWuX",
      "decision": "BUY",
      "current_price": 0.0013861947661561761,
      "volume": 1044.4358023406,
      "fdv": 1385387.054,
      "reserve": 128255.8088,
      "buys": 3,
      "sells": 13,
      "price_change": 1.422,
      "ai_reasoning": "**Decision:** WATCH  \n**Reasoning:** The provided ratio (0.2) indicates more sells than buys, which falls under \"high risk\" per the guidelines. However, the trade flow momentum is stable, and the price change is minimal (+1.4%), suggesting potential for a conservative approach. The low volume and low volatility further support a cautious watch rather than an immediate buy.\n\n**Parameters:**  \n- **Limit Order:** Low volatility \u2192 **0% to -2%** (enter near market).  \n- **Take Profit:** Low volume \u2192 **+5% to +10%**.  \n- **Stop Loss:** Low volatility \u2192 **-5% to -8%**.  \n- **Time Frame:** Low volume \u2192 **2 hours to 6 hours**.  \n\n**Conclusion:** Maintain a watchful stance, using the above parameters to evaluate further opportunities while mitigating risk.",
      "trading_params": {
        "limit_order_price": 0.0013861947661561761,
        "limit_order_pct": 0,
        "take_profit_price": 0.001524814242771794,
        "take_profit_pct": 10,
        "stop_loss_price": 0.0013168850278483673,
        "stop_loss_pct": -5,
        "time_frame": "1h"
      }
    },
    {
      "name": "Foid / SOL",
      "mint": "6x9F82hqxdHx29UKPrH2Yk6kTFzbaKK46yZe726Lpump",
      "pool": "3bz1yN3r6Z1XoLbX6Qtdwhp3QPym62MwFMcNTTn3Himv",
      "chart_url": "https://geckoterminal.com/solana/pools/3bz1yN3r6Z1XoLbX6Qtdwhp3QPym62MwFMcNTTn3Himv",
      "decision": "BUY",
      "current_price": 0.00013583873751299457,
      "volume": 654.2680945163,
      "fdv": 137166.7449,
      "reserve": 39147.0759,
      "buys": 6,
      "sells": 7,
      "price_change": 4.476,
      "ai_reasoning": "WATCH (Buy/Sell Ratio <1.0 indicates high risk, but recent +4.5% price rise and stable flow momentum suggest cautious monitoring)  \n\n**Parameters (if BUY):**  \nBUY | Limit:-2% | TP:+8% | SL:-6% | Time:3h  \n\n**Rationale:**  \n- **Ratio <1.0** (0.9) \u2192 High risk, but recent price increase (+4.5%) and stable flow momentum (STABLE) suggest potential for reversal.  \n- **Low volatility** (4.5% price change) \u2192 Limit at -2% (wait for dip).  \n- **Low volume** ($654) \u2192 Take profit at +8% (moderate exit).  \n- **Low volatility** \u2192 Stop loss at -6% (balance risk).  \n- **Low volume** \u2192 Short time frame (3h) for quick entry/exit.  \n\n**Decision:** WATCH (Monitor for potential reversal; avoid aggressive entry due to weak buy pressure).",
      "trading_params": {
        "limit_order_price": 0.00013312196276273468,
        "limit_order_pct": -2.0,
        "take_profit_price": 0.00014377171978375346,
        "take_profit_pct": 8.0,
        "stop_loss_price": 0.0001251346449969706,
        "stop_loss_pct": -6.0,
        "time_frame": "3h"
      }
    }
  ]
}