{
  "timestamp": "2026-02-03T01:41:32.870125",
  "scan_time": "20260203_014132",
  "total_tokens": 3,
  "buy_signals": 3,
  "watch_signals": 0,
  "skip_signals": 0,
  "tokens": [
    {
      "name": "Phil / SOL",
      "mint": "ZfcJMRtaC9GNRrzYomvgqgN3mP6KTSvub3Gr9pXpump",
      "pool": "DPE6QVvw2YLc8558Vr5MGsnwwKSDxT67376rFDnHput5",
      "chart_url": "https://geckoterminal.com/solana/pools/DPE6QVvw2YLc8558Vr5MGsnwwKSDxT67376rFDnHput5",
      "decision": "BUY",
      "current_price": 9.679274154410653e-05,
      "volume": 1424.6632045872,
      "fdv": 94126.85292,
      "reserve": 30072.4738,
      "buys": 11,
      "sells": 6,
      "price_change": 2.457,
      "ai_reasoning": "**Reasoning:**  \n- **BUY/SELL PRESSURE:** Ratio (1.8) > 1.5 indicates strong buying, with **STABLE momentum**. Aggressive entry via market order (0% limit) aligns with strong buying pressure.  \n- **LIMIT ORDER:** Low volatility (2.5% price change) + strong buying pressure \u2192 **0% limit** (market order).  \n- **TAKE PROFIT:** Low volume ($1,425) \u2192 **+10%** (upper end of low-volume range).  \n- **STOP LOSS:** Low volatility \u2192 **-8%** (upper end of low-volatility SL range).  \n- **TIME FRAME:** Low volume \u2192 **2h** (shortest end of low-volume timeframe).  \n\n**Key Data Alignment:**  \n- Recent 300 trades (160 buys, 140 sells) + 100-trade flow analysis (65% buys in all thirds) confirm **buying dominance**.  \n- No signs of accelerating/decelerating momentum, so **standard aggressive parameters** apply.",
      "trading_params": {
        "limit_order_price": 9.679274154410653e-05,
        "limit_order_pct": 0.0,
        "take_profit_price": 0.0001064720156985172,
        "take_profit_pct": 10.0,
        "stop_loss_price": 8.904932222057801e-05,
        "stop_loss_pct": -8.0,
        "time_frame": "2h"
      }
    },
    {
      "name": "Ad Astra / SOL",
      "mint": "4KV5L2ZXgNAvXS6acEWVZratZWi2p8MumkPxRZqcpump",
      "pool": "JD7yBXviXTdRFHCQpZdDSznQHqa2kQZPqi61gPvrJj8P",
      "chart_url": "https://geckoterminal.com/solana/pools/JD7yBXviXTdRFHCQpZdDSznQHqa2kQZPqi61gPvrJj8P",
      "decision": "BUY",
      "current_price": 1.2798300707325248e-05,
      "volume": 1478.4873186118,
      "fdv": 12423.76678,
      "reserve": 9300.5914,
      "buys": 28,
      "sells": 13,
      "price_change": 29.095,
      "ai_reasoning": "**Rationale**:  \n- **BUY/SELL PRESSURE**: Ratio of 2.2 (>1.5) indicates strong buying, combined with stable momentum (standard parameters).  \n- **LIMIT ORDER**: Strong buying pressure overrides volatility (29.1% price change) \u2192 0% limit (market entry).  \n- **TAKE PROFIT**: Low volume (<$3k) \u2192 +5% to +10% (aggressive early exit).  \n- **STOP LOSS**: Low volatility \u2192 -5% to -8% (conservative SL).  \n- **TIME FRAME**: Low volume \u2192 2h to 6h; stable momentum aligns with 4h holding period.",
      "trading_params": {
        "limit_order_price": 1.2798300707325248e-05,
        "limit_order_pct": 0.0,
        "take_profit_price": 1.4078130778057774e-05,
        "take_profit_pct": 10.0,
        "stop_loss_price": 1.1774436650739229e-05,
        "stop_loss_pct": -8.0,
        "time_frame": "4h"
      }
    },
    {
      "name": "BLM / SOL",
      "mint": "6QBjp4h115hvHsWjisRCRKrfECGKFMdSkx1giYCjpump",
      "pool": "Dw9jTRcrHCm1kqRHvWxxtKtTKW7BXt8jCwChMgnAQdKd",
      "chart_url": "https://geckoterminal.com/solana/pools/Dw9jTRcrHCm1kqRHvWxxtKtTKW7BXt8jCwChMgnAQdKd",
      "decision": "BUY",
      "current_price": 0.00012993688026101166,
      "volume": 6100.8418836871,
      "fdv": 129819.9014,
      "reserve": 31671.4127,
      "buys": 34,
      "sells": 26,
      "price_change": 16.815,
      "ai_reasoning": "BUY | Limit:-5% | TP:+5% | SL:-8% | Time:2h",
      "trading_params": {
        "limit_order_price": 0.00012344003624796106,
        "limit_order_pct": -5.0,
        "take_profit_price": 0.00012961203806035912,
        "take_profit_pct": 5.0,
        "stop_loss_price": 0.00011356483334812419,
        "stop_loss_pct": -8.0,
        "time_frame": "2h"
      }
    }
  ]
}