{
  "timestamp": "2026-01-03T17:32:33.977228",
  "scan_time": "20260103_173233",
  "total_tokens": 9,
  "buy_signals": 7,
  "watch_signals": 2,
  "skip_signals": 0,
  "tokens": [
    {
      "name": "Marlee / SOL",
      "mint": "Hr8QsyUw1iVoM6fNcpsFW4eTbpWr4xw1XDGWJUmPpump",
      "pool": "AA5WvrRqUzwu9fnVPX4eDaPnaBDZGASzfPzHsiFmArnB",
      "chart_url": "https://geckoterminal.com/solana/pools/AA5WvrRqUzwu9fnVPX4eDaPnaBDZGASzfPzHsiFmArnB",
      "decision": "BUY",
      "current_price": 0.00022979317398112852,
      "volume": 8833.1503615667,
      "fdv": 220374.2634,
      "reserve": 48164.7163,
      "buys": 23,
      "sells": 62,
      "price_change": 5.752,
      "ai_reasoning": "WATCH (High sell pressure with ratio <1.0, but stable flow momentum suggests potential reversal)  \n**Parameters (for potential entry):**  \nLimit:-2% | TP:+10% | SL:-5% | Time:4h  \n\n**Rationale:**  \n- **Buy/Sell Ratio:** 0.4 (strong sell pressure, but flow momentum is stable, indicating possible reversal).  \n- **Volume:** Low ($8,833) \u2192 Use tighter TP (+10%) and SL (-5%).  \n- **Price Change:** +5.8% (low volatility) \u2192 Enter near market (-2% limit).  \n- **Time Frame:** 4h (medium volatility, balanced flow).  \n\n**Note:** Watch for signs of buying momentum or volume spikes to confirm reversal.",
      "trading_params": {
        "limit_order_price": 0.00022519731050150594,
        "limit_order_pct": -2.0,
        "take_profit_price": 0.00024771704155165654,
        "take_profit_pct": 10.0,
        "stop_loss_price": 0.00021393744497643063,
        "stop_loss_pct": -5.0,
        "time_frame": "4h"
      }
    },
    {
      "name": "KREDO / SOL",
      "mint": "F2hgieC18MeUWaWMoyaxLSQCzS7yAjRz1HgmbGAEpump",
      "pool": "A1ryGUggxDq6GjckjZvc6R6Ss3tPM6wKqRUb55P6kRkY",
      "chart_url": "https://geckoterminal.com/solana/pools/A1ryGUggxDq6GjckjZvc6R6Ss3tPM6wKqRUb55P6kRkY",
      "decision": "BUY",
      "current_price": 8.966684752280186e-05,
      "volume": 2219.9028195779,
      "fdv": 89472.648,
      "reserve": 29214.3317,
      "buys": 17,
      "sells": 14,
      "price_change": 22.91,
      "ai_reasoning": "**Reasoning:**  \n- **BUY/SELL PRESSURE:** Ratio of 1.2 (balanced) with **STABLE momentum** \u2192 conservative BUY.  \n- **LIMIT ORDER:** Medium volatility (+22.9% price change) \u2192 -2% to -5% range; chosen -3% for balance.  \n- **TAKE PROFIT:** Low volume (<$3k) \u2192 +5% to +10% range; selected +7% for early liquidity.  \n- **STOP LOSS:** Medium volatility \u2192 -8% to -15% range; set at -10% for risk management.  \n- **TIME FRAME:** Medium volatility \u2192 30min to 2h; optimized to 1h for quick execution.  \n\n**Key Drivers:** Strong buying in the middle third (68% buys) and recent flow stability justify a conservative BUY with tighter SL/TP.",
      "trading_params": {
        "limit_order_price": 8.69768420971178e-05,
        "limit_order_pct": -3.0,
        "take_profit_price": 9.306522104391606e-05,
        "take_profit_pct": 7.0,
        "stop_loss_price": 7.827915788740602e-05,
        "stop_loss_pct": -10.0,
        "time_frame": "1h"
      }
    },
    {
      "name": "TRAX / SOL",
      "mint": "Dk2pDpyS1H6S5TCv3Afx8bmxJb1XbsWBJbReXtjipump",
      "pool": "CBEq92TwEMjRGb4Kxyosfhez7Ufpgs6A6HiVdMTNWRC3",
      "chart_url": "https://geckoterminal.com/solana/pools/CBEq92TwEMjRGb4Kxyosfhez7Ufpgs6A6HiVdMTNWRC3",
      "decision": "BUY",
      "current_price": 0.0003155421178579554,
      "volume": 11286.3655478255,
      "fdv": 313305.6859,
      "reserve": 56338.9257,
      "buys": 41,
      "sells": 43,
      "price_change": 1.596,
      "ai_reasoning": "**Reasoning:**  \n- **Buy/Sell Ratio (1.0):** Balanced, but trade flow shows strong buying in the middle third (51% buys). Momentum is stable, so standard parameters apply.  \n- **Limit Order:** Low volatility (+1.6% price change) + strong buying pressure in middle third \u2192 **0%** (market order).  \n- **Take Profit:** Medium volume ($11k) \u2192 **+15%** (mid-range of +10%\u2013+20%).  \n- **Stop Loss:** Low volatility \u2192 **-6%** (mid-range of -5%\u2013-8%).  \n- **Time Frame:** Medium volume \u2192 **4h** (balance between quick trades and holding for liquidity).  \n\n**Decision:** BUY with aggressive entry (market order) and moderate risk/reward.",
      "trading_params": {
        "limit_order_price": 0.0003155421178579554,
        "limit_order_pct": 0.0,
        "take_profit_price": 0.0003628734355366487,
        "take_profit_pct": 15.0,
        "stop_loss_price": 0.0002966095907864781,
        "stop_loss_pct": -6.0,
        "time_frame": "4h"
      }
    },
    {
      "name": "Marlee / SOL",
      "mint": "5sJShHp4FuqsoYdH8sRpcJTA9DPmrQFZvNmVZpNXpump",
      "pool": "3C7wTaYQCbo6uCw1yD44btcM4fZpENstPLGTGZLeL7S3",
      "chart_url": "https://geckoterminal.com/solana/pools/3C7wTaYQCbo6uCw1yD44btcM4fZpENstPLGTGZLeL7S3",
      "decision": "BUY",
      "current_price": 3.258965957160214e-05,
      "volume": 2078.2464155643,
      "fdv": 32589.65957,
      "reserve": 19374.9022,
      "buys": 8,
      "sells": 11,
      "price_change": 4.624,
      "ai_reasoning": "WATCH (Buy/Sell Ratio < 1.0 indicates stronger sell pressure, but stable trade flow suggests potential reversal. Low volume and moderate price change warrant caution.)",
      "trading_params": {
        "limit_order_price": 3.258965957160214e-05,
        "limit_order_pct": 0,
        "take_profit_price": 3.584862552876235e-05,
        "take_profit_pct": 10,
        "stop_loss_price": 3.096017659302203e-05,
        "stop_loss_pct": -5,
        "time_frame": "1h"
      }
    },
    {
      "name": "SBS / SOL",
      "mint": "8wmCd8asNtuieLmTZz15Vcby5UY1CN8gfAjRhamSpump",
      "pool": "E3YKFiM5kyCbSe7fmDQgSxAojBjE7r7D9aRxWF4wXPeu",
      "chart_url": "https://geckoterminal.com/solana/pools/E3YKFiM5kyCbSe7fmDQgSxAojBjE7r7D9aRxWF4wXPeu",
      "decision": "BUY",
      "current_price": 9.136636353337319e-06,
      "volume": 836.8180575956,
      "fdv": 9097.103197,
      "reserve": 5925.6547,
      "buys": 16,
      "sells": 2,
      "price_change": 32.372,
      "ai_reasoning": "**Rationale:**  \n- **Buy/Sell Ratio (8.0):** Strong buying pressure (>1.5), with stable momentum.  \n- **Limit Order:** Strong buying pressure overrides medium volatility (32.4% price change), so enter at market (0%).  \n- **Take Profit:** Low volume (<$3k) \u2192 +5% to +10% (targeting +7%).  \n- **Stop Loss:** Medium volatility (32.4% price change) \u2192 -8% to -15% (SL at -10%).  \n- **Time Frame:** Low volume \u2192 2h to 6h (midpoint at 4h).  \n- **Flow Momentum:** Stable, so standard parameters apply.",
      "trading_params": {
        "limit_order_price": 9.136636353337319e-06,
        "limit_order_pct": 0.0,
        "take_profit_price": 9.776200898070932e-06,
        "take_profit_pct": 7.0,
        "stop_loss_price": 8.222972718003587e-06,
        "stop_loss_pct": -10.0,
        "time_frame": "4h"
      }
    },
    {
      "name": "fish / SOL",
      "mint": "CmgJ1PobhUqB7MEa8qDkiG2TUpMTskWj8d9JeZWSpump",
      "pool": "7YW47DAivaQxHHYVRsP2eGzMcAMGx4czhdJ7XEFUMoYs",
      "chart_url": "https://geckoterminal.com/solana/pools/7YW47DAivaQxHHYVRsP2eGzMcAMGx4czhdJ7XEFUMoYs",
      "decision": "BUY",
      "current_price": 0.0006985693841782613,
      "volume": 827.6353742557,
      "fdv": 698563.421383719,
      "reserve": 101663.0931,
      "buys": 7,
      "sells": 2,
      "price_change": 0.883,
      "ai_reasoning": "**Rationale:**  \n- **Buy/Sell Pressure:** Ratio of 3.5 indicates strong buying, with stable momentum.  \n- **Limit Order:** Strong buying pressure overrides volatility considerations (0% market entry).  \n- **Take Profit:** Low volume ($828) warrants conservative +5%\u2013+10% (using +10% for liquidity).  \n- **Stop Loss:** Low volatility (-5%\u2013-8%) with -7% as a balanced risk threshold.  \n- **Time Frame:** Stable momentum and low volume suggest a 4-hour holding period for quick exits.",
      "trading_params": {
        "limit_order_price": 0.0006985693841782613,
        "limit_order_pct": -0.0,
        "take_profit_price": 0.0007684263225960874,
        "take_profit_pct": 10.0,
        "stop_loss_price": 0.0006496695272857829,
        "stop_loss_pct": -7.0,
        "time_frame": "4h"
      }
    },
    {
      "name": "DUCK / SOL",
      "mint": "B79HpCzajp6XE41ezUoU8RwJqnfxS8oLsWcs4zQ2pump",
      "pool": "4yoJhwDiZL69SLBopuDWRqJVcMagx4XhprgiD5BfYaKD",
      "chart_url": "https://geckoterminal.com/solana/pools/4yoJhwDiZL69SLBopuDWRqJVcMagx4XhprgiD5BfYaKD",
      "decision": "WATCH",
      "current_price": 0.0007499622066256832,
      "volume": 771.3057349896,
      "fdv": 750324.1928,
      "reserve": 101172.9746,
      "buys": 1,
      "sells": 7,
      "price_change": 2.828,
      "ai_reasoning": "### Analysis and Decision\n\n**1. Buy/Sell Ratio (Conflicting Data):**  \nThe provided ratio is **0.1**, which implies **more sells than buys**. However, the **trade flow data** shows **141 buys** and **159 sells** across 300 trades (buys/sells = 0.887), suggesting **slightly more sells**. The **recent 5 trades** (3 buys, 2 sells) show **strong buy pressure** (buys/sells = 1.5). This inconsistency suggests a possible **data entry error**, but we'll proceed with the **trade flow analysis** (buys/sells = 0.887, slightly below 1.0).  \n\n**Rule 1 (Buy/Sell Ratio):**  \n- If **buys/sells < 1.0**, **SKIP or WATCH**.  \n- Given the **recent strong buy pressure** (1.5), this might indicate **contrarian momentum**.  \n\n**2. Price Change and Volatility:**  \n- **+2.8%** price increase: **medium volatility**.  \n\n**3. Volume:**  \n- **$771** volume: **low volume**.  \n\n**4. Trade Flow Momentum:**  \n- **STABLE**: Indicates **no strong directional bias**.  \n\n---\n\n### Final Decision: **WATCH**  \n- **Reason:** Despite recent strong buy pressure, the overall ratio (0.887) and stable momentum suggest **caution**.  \n- **Risk:** Potential for a **short-term reversal** due to low volume and mixed signals.  \n\n---\n\n### Recommended Parameters (Based on Low Volatility and Stable Momentum):  \n- **Limit Order:** **-2% to -5%** (enter near market).  \n- **Take Profit:** **+5% to +10%** (low volume, conservative).  \n- **Stop Loss:** **-5% to -8%** (low volatility, risk management).  \n- **Time Frame:** **2h to 6h** (short-term, stable momentum).  \n\n**Note:** Monitor for **volume spikes** or **price divergence** to confirm trends. Adjust strategy based on real-time data.",
      "trading_params": {
        "limit_order_price": 0.0007499622066256832,
        "limit_order_pct": 0,
        "take_profit_price": 0.0008249584272882516,
        "take_profit_pct": 10,
        "stop_loss_price": 0.000712464096294399,
        "stop_loss_pct": -5,
        "time_frame": "1h"
      }
    },
    {
      "name": "ai16zjeju / SOL",
      "mint": "F7Kgj2CACk4WWgZy769NkjHgJ4AdWPwoANynwmvQpump",
      "pool": "Gt1yNTqviLuF3HSPrezfHd3ZhrCuL1RiGFCbzjCgAjGp",
      "chart_url": "https://geckoterminal.com/solana/pools/Gt1yNTqviLuF3HSPrezfHd3ZhrCuL1RiGFCbzjCgAjGp",
      "decision": "BUY",
      "current_price": 1.053082830866597e-05,
      "volume": 937.3676992475,
      "fdv": 10530.82831,
      "reserve": 6375.119,
      "buys": 13,
      "sells": 3,
      "price_change": 16.826,
      "ai_reasoning": "**Rationale:**  \n- **BUY Signal:** Buy/Sell Ratio (4.3) > 1.5 with stable momentum indicates strong buying pressure.  \n- **Limit Order:** Strong buying pressure (ratio >1.5) overrides medium volatility (-2% to -5%) and uses **0%** (market entry).  \n- **Take Profit:** Low volume (<$3k) + stable momentum \u2192 **+10%** (aggressive vs standard +5%\u2013+10% range).  \n- **Stop Loss:** Low volume \u2192 **-8%** (upper end of -5%\u2013-8% range for tighter risk management).  \n- **Time Frame:** Low volume + stable momentum \u2192 **4h** (midpoint of 2h\u20136h).  \n\n**Key Factors:**  \n- Recent 5 trades (2 buys) and previous 5 trades (3 buys) reinforce buying momentum.  \n- Trade flow is balanced (49%\u201351% buys across thirds), confirming no sudden acceleration.  \n- Price change (+16.8%) is medium volatility, but strong buying pressure dominates.",
      "trading_params": {
        "limit_order_price": 1.053082830866597e-05,
        "limit_order_pct": 0.0,
        "take_profit_price": 1.1583911139532567e-05,
        "take_profit_pct": 10.0,
        "stop_loss_price": 9.688362043972692e-06,
        "stop_loss_pct": -8.0,
        "time_frame": "4h"
      }
    },
    {
      "name": "learing / SOL",
      "mint": "3kC6gheQ5fxK8iKWWDHeomHU5Z6U2dUWfqEK6dpLpump",
      "pool": "3HsBgq8qDgYZQipmQ2kM7Xmpdu2nQCeUw1749DktTm87",
      "chart_url": "https://geckoterminal.com/solana/pools/3HsBgq8qDgYZQipmQ2kM7Xmpdu2nQCeUw1749DktTm87",
      "decision": "WATCH",
      "current_price": 0.0003617708358746715,
      "volume": 940.2508529835,
      "fdv": 360333.6613,
      "reserve": 79904.0967,
      "buys": 2,
      "sells": 6,
      "price_change": 1.687,
      "ai_reasoning": "WATCH (High sell pressure with ratio 0.3, but stable flow momentum; low volume may indicate limited liquidity).",
      "trading_params": {
        "limit_order_price": 0.0003617708358746715,
        "limit_order_pct": 0,
        "take_profit_price": 0.00039794791946213865,
        "take_profit_pct": 10,
        "stop_loss_price": 0.00034368229408093787,
        "stop_loss_pct": -5,
        "time_frame": "1h"
      }
    }
  ]
}