{
  "timestamp": "2026-02-10T06:18:52.757795",
  "scan_time": "20260210_061852",
  "total_tokens": 3,
  "buy_signals": 3,
  "watch_signals": 0,
  "skip_signals": 0,
  "tokens": [
    {
      "name": "REX / SOL",
      "mint": "6Uz2zrQRSyyPUmbuJMpP2bn86CgnESvod6yUPMefpump",
      "pool": "FMmfrUk2A498xhsSSxB2DTD7tzXePdqRvnxNmWmWna8s",
      "chart_url": "https://geckoterminal.com/solana/pools/FMmfrUk2A498xhsSSxB2DTD7tzXePdqRvnxNmWmWna8s",
      "decision": "BUY",
      "current_price": 3.6838696353937195e-05,
      "volume": 1228.9840464024,
      "fdv": 36679.68227,
      "reserve": 16318.7402,
      "buys": 17,
      "sells": 14,
      "price_change": 7.61,
      "ai_reasoning": "**Rationale:**  \n- **BUY/SELL PRESSURE:** Ratio 1.2 (balanced) with stable momentum \u2192 conservative BUY.  \n- **LIMIT ORDER:** Low volatility (7.6% price change) + balanced ratio \u2192 -2% (slightly below current price).  \n- **TAKE PROFIT:** Low volume ($1,229) \u2192 +8% (mid-range for liquidity).  \n- **STOP LOSS:** Low volatility \u2192 -6% (moderate risk buffer).  \n- **TIME FRAME:** Low volume + stable momentum \u2192 2h-6h (medium-term holding).  \n\n**Key Observations:**  \n- Recent 5 trades (0 buys) suggest short-term indecision, but overall flow is stable.  \n- Volume is low, so aggressive TP/SL is avoided to preserve capital.  \n- The +7.6% price surge hints at potential continuation, but cautious entry is warranted.",
      "trading_params": {
        "limit_order_price": 3.610192242685845e-05,
        "limit_order_pct": -2.0,
        "take_profit_price": 3.899007622100713e-05,
        "take_profit_pct": 8.0,
        "stop_loss_price": 3.393580708124695e-05,
        "stop_loss_pct": -6.0,
        "time_frame": "2h"
      }
    },
    {
      "name": "Compozy / SOL",
      "mint": "CPwsANnDBaPF1jrYPkix372JoCtcWeBCH4ctEBapump",
      "pool": "Eu6jB4TzDD8duorjviJDTVrmB8fjjF1b5t8N8vhvr7Jj",
      "chart_url": "https://geckoterminal.com/solana/pools/Eu6jB4TzDD8duorjviJDTVrmB8fjjF1b5t8N8vhvr7Jj",
      "decision": "BUY",
      "current_price": 1.1677607455051059e-05,
      "volume": 3605.8386517881,
      "fdv": 11791.1576,
      "reserve": 5531.6677,
      "buys": 44,
      "sells": 30,
      "price_change": 2.061,
      "ai_reasoning": "**Rationale:**  \n- **Buy/Sell Ratio (1.5):** Strong buying pressure (>1.5) triggers aggressive entry (0% limit).  \n- **Momentum (STABLE):** Standard parameters apply, balancing risk with moderate TP/SLL.  \n- **Price Change (+2.1%):** Low volatility (<10%) justifies 0% limit (market order).  \n- **Volume ($3,606):** Low volume dictates tighter TP (+8%) and SL (-6%) to preserve capital.  \n- **Time Frame:** 4h aligns with low-volume liquidity windows for quick exits.",
      "trading_params": {
        "limit_order_price": 1.1677607455051059e-05,
        "limit_order_pct": 0.0,
        "take_profit_price": 1.2611816051455145e-05,
        "take_profit_pct": 8.0,
        "stop_loss_price": 1.0976951007747994e-05,
        "stop_loss_pct": -6.0,
        "time_frame": "4h"
      }
    },
    {
      "name": "STORM / SOL",
      "mint": "C7EUfoBEy3zzSGHjHV9ps1uNbGCUdJDUoqomXEazpump",
      "pool": "8FGtSYGPEq9MmbjGCWwSdeBhXuXUgnjS22XuWBiWzm72",
      "chart_url": "https://geckoterminal.com/solana/pools/8FGtSYGPEq9MmbjGCWwSdeBhXuXUgnjS22XuWBiWzm72",
      "decision": "BUY",
      "current_price": 5.1525417354562984e-05,
      "volume": 1464.4399314558,
      "fdv": 52259.68886,
      "reserve": 17797.2985,
      "buys": 22,
      "sells": 5,
      "price_change": 1.943,
      "ai_reasoning": "**Reasoning:**  \n- **Buy/Sell Pressure:** Ratio of 4.4 (strong buying) + stable momentum \u2192 aggressive BUY with 0% limit (market entry).  \n- **Limit Order:** Low volatility (+1.9%) + strong buying pressure \u2192 0% (no waiting).  \n- **Take Profit:** Low volume (<$3k) \u2192 +5%\u2013+10% range; chosen +8% for balanced liquidity.  \n- **Stop Loss:** Low volatility \u2192 -5%\u2013-8% range; chosen -6% for risk management.  \n- **Time Frame:** Low volume + stable momentum \u2192 4h (mid-range for moderate liquidity).",
      "trading_params": {
        "limit_order_price": 5.1525417354562984e-05,
        "limit_order_pct": 0.0,
        "take_profit_price": 5.5647450742928026e-05,
        "take_profit_pct": 8.0,
        "stop_loss_price": 4.8433892313289205e-05,
        "stop_loss_pct": -6.0,
        "time_frame": "4h"
      }
    }
  ]
}