{
  "timestamp": "2026-02-13T12:56:26.772067",
  "scan_time": "20260213_125626",
  "total_tokens": 3,
  "buy_signals": 3,
  "watch_signals": 0,
  "skip_signals": 0,
  "tokens": [
    {
      "name": "BongoCat / SOL",
      "mint": "9gdB6CmfBW7Cer73x6aGiqqkGEcuzpaZLJkhJVEGpump",
      "pool": "GK48AvexEphHNsHKnSeWaVQmCoq1UZV1fySKAwASNeNP",
      "chart_url": "https://geckoterminal.com/solana/pools/GK48AvexEphHNsHKnSeWaVQmCoq1UZV1fySKAwASNeNP",
      "decision": "BUY",
      "current_price": 3.4754959170251315e-05,
      "volume": 4679.476541468,
      "fdv": 35369.783,
      "reserve": 13963.9382,
      "buys": 80,
      "sells": 25,
      "price_change": 32.794,
      "ai_reasoning": "BUY | Limit:0% | TP:+10% | SL:-8% | Time:4h",
      "trading_params": {
        "limit_order_price": 3.4754959170251315e-05,
        "limit_order_pct": 0.0,
        "take_profit_price": 3.823045508727645e-05,
        "take_profit_pct": 10.0,
        "stop_loss_price": 3.197456243663121e-05,
        "stop_loss_pct": -8.0,
        "time_frame": "4h"
      }
    },
    {
      "name": "PILLO / SOL",
      "mint": "9a6SEQ7qBnWEmzz4Vpeq55a7tcubu26wJwkwCM5Cpump",
      "pool": "AFMn7kGXvUJ3H69UkmFzqUR3VwzexbXqHswYaEPhzq8L",
      "chart_url": "https://geckoterminal.com/solana/pools/AFMn7kGXvUJ3H69UkmFzqUR3VwzexbXqHswYaEPhzq8L",
      "decision": "BUY",
      "current_price": 3.308740515285813e-05,
      "volume": 4218.1738625957,
      "fdv": 32136.12083,
      "reserve": 13257.7495,
      "buys": 53,
      "sells": 47,
      "price_change": 5.059,
      "ai_reasoning": "BUY | Limit:-2% | TP:+10% | SL:-8% | Time:4h",
      "trading_params": {
        "limit_order_price": 3.242565704980097e-05,
        "limit_order_pct": -2.0,
        "take_profit_price": 3.566822275478107e-05,
        "take_profit_pct": 10.0,
        "stop_loss_price": 2.9831604485816894e-05,
        "stop_loss_pct": -8.0,
        "time_frame": "4h"
      }
    },
    {
      "name": "SISYPHUS / SOL",
      "mint": "7Rni7A9Sa8qut96FBEP5D3pbkkRnwMgRNqHS3hEFpump",
      "pool": "DBTFob2rW2obQQvKTcznKK3QkJVVYK6HynKyaWzPh2dG",
      "chart_url": "https://geckoterminal.com/solana/pools/DBTFob2rW2obQQvKTcznKK3QkJVVYK6HynKyaWzPh2dG",
      "decision": "BUY",
      "current_price": 4.0759222980030396e-05,
      "volume": 2013.9183444116,
      "fdv": 40282.93057,
      "reserve": 15514.4838,
      "buys": 12,
      "sells": 18,
      "price_change": 4.505,
      "ai_reasoning": "**Decision:** Watch  \n**Limit Order:** -2% to -5% (medium volatility)  \n**Take Profit:** +5% to +10% (low volume)  \n**Stop Loss:** -8% to -15% (medium volatility)  \n**Time Frame:** 2h to 6h (low volume)  \n\n---\n\n**Rationale:**  \n1. **Buy/Sell Ratio:** While the user specifies a ratio of 0.7 (suggesting more sells), the recent 300-trades data shows 155 buys and 145 sells (ratio ~1.07), indicating a **balanced** market. This aligns with Rule 1, which recommends **watching** or a **conservative buy**.  \n2. **Price Change:** +4.5% (medium volatility) \u2192 Rule 2 applies: limit order at **-2% to -5%**.  \n3. **Volume:** $2,014 (low volume) \u2192 Rule 3: take profit at **+5% to +10%**.  \n4. **Volatility:** Medium \u2192 Rule 4: stop loss at **-8% to -15%**.  \n5. **Trade Flow:** Stable \u2192 Rule 1: standard parameters for a balanced market.  \n\n**Conclusion:** The market shows a balanced buy/sell dynamic with stable flow. While the ratio may be ambiguous, the recent trades suggest a **watch** strategy with conservative parameters.",
      "trading_params": {
        "limit_order_price": 4.0759222980030396e-05,
        "limit_order_pct": 0,
        "take_profit_price": 4.483514527803344e-05,
        "take_profit_pct": 10,
        "stop_loss_price": 3.8721261831028874e-05,
        "stop_loss_pct": -5,
        "time_frame": "1h"
      }
    }
  ]
}