{
  "timestamp": "2026-02-10T12:51:52.602780",
  "scan_time": "20260210_125152",
  "total_tokens": 3,
  "buy_signals": 3,
  "watch_signals": 0,
  "skip_signals": 0,
  "tokens": [
    {
      "name": "PoopWhale / SOL",
      "mint": "HB1GX2Vkh8KosPePZ5zBtbLgLQm7JQXpmgz7ADM4pump",
      "pool": "AfKYPtGK2zDTS5LeYJvDW13wgv6oS5Adnjwc8RrNgSM6",
      "chart_url": "https://geckoterminal.com/solana/pools/AfKYPtGK2zDTS5LeYJvDW13wgv6oS5Adnjwc8RrNgSM6",
      "decision": "BUY",
      "current_price": 6.839508132161089e-05,
      "volume": 13625.7856800712,
      "fdv": 67831.18753,
      "reserve": 19781.648,
      "buys": 87,
      "sells": 80,
      "price_change": 28.503,
      "ai_reasoning": "**Rationale:**  \n- **Buy/Sell Ratio (1.1):** Balanced, but recent trades (161 buys, 139 sells) and trade flow (57% buys in all thirds) indicate **strong buying pressure**. Rule 1 overrides the ratio with **aggressive BUY** parameters.  \n- **Price Change (+28.5%):** Medium volatility, but **strong buying pressure** (Rule 2) dictates **0% limit** (market order).  \n- **Volume ($13,626):** Medium volume \u2192 TP: +10% to +20% (midpoint: +15%).  \n- **Volatility:** Medium \u2192 SL: -8% to -15% (midpoint: -10%).  \n- **Momentum (STABLE):** Standard time frame of **1h** (30min\u20132h range).  \n\n**Decision:** BUY with aggressive entry, mid-range TP, and moderate SL to capitalize on sustained buying momentum.",
      "trading_params": {
        "limit_order_price": 6.839508132161089e-05,
        "limit_order_pct": 0.0,
        "take_profit_price": 7.865434351985252e-05,
        "take_profit_pct": 15.0,
        "stop_loss_price": 6.15555731894498e-05,
        "stop_loss_pct": -10.0,
        "time_frame": "1h"
      }
    },
    {
      "name": "CLOUT / SOL",
      "mint": "Cwq13pofafd7KNbWBabULgt7QC1w53NjiPgES49Ypump",
      "pool": "6kxFj9S4KDGkzUJ5hprtvRjB6iiAu9ySDp87ERoVcQiZ",
      "chart_url": "https://geckoterminal.com/solana/pools/6kxFj9S4KDGkzUJ5hprtvRjB6iiAu9ySDp87ERoVcQiZ",
      "decision": "BUY",
      "current_price": 0.000125102048544037,
      "volume": 6268.255192331,
      "fdv": 121699.009630981,
      "reserve": 31883.5356,
      "buys": 43,
      "sells": 33,
      "price_change": 24.595,
      "ai_reasoning": "**Reasoning:**  \n- **BUY/SELL PRESSURE:** Ratio of 1.3 (balanced) with **strong buying flow** in middle third (60% buys) and recent momentum (STABLE). Conservative BUY with aggressive parameters due to strong buying pressure.  \n- **LIMIT ORDER:** Strong buying pressure overrides medium volatility (24.6% price change) \u2192 0% (market order).  \n- **TAKE PROFIT:** Low volume (<$3k) \u2192 +10% (early exit with liquidity).  \n- **STOP LOSS:** Low volatility \u2192 -8% (tight stop to preserve capital).  \n- **TIME FRAME:** Stable momentum + low volume \u2192 4h (balanced risk/reward).",
      "trading_params": {
        "limit_order_price": 0.000125102048544037,
        "limit_order_pct": 0.0,
        "take_profit_price": 0.0001376122533984407,
        "take_profit_pct": 10.0,
        "stop_loss_price": 0.00011509388466051404,
        "stop_loss_pct": -8.0,
        "time_frame": "4h"
      }
    },
    {
      "name": "STORM / SOL",
      "mint": "C7EUfoBEy3zzSGHjHV9ps1uNbGCUdJDUoqomXEazpump",
      "pool": "8FGtSYGPEq9MmbjGCWwSdeBhXuXUgnjS22XuWBiWzm72",
      "chart_url": "https://geckoterminal.com/solana/pools/8FGtSYGPEq9MmbjGCWwSdeBhXuXUgnjS22XuWBiWzm72",
      "decision": "BUY",
      "current_price": 7.977440113510012e-05,
      "volume": 2233.1917341094,
      "fdv": 82758.4213,
      "reserve": 22561.51,
      "buys": 22,
      "sells": 22,
      "price_change": 7.362,
      "ai_reasoning": "### **Decision**: **BUY**  \n**Rationale**:  \n- **Buy/Sell Ratio**: While the user explicitly states the ratio is **1.0**, the **recent trades (189 buys, 111 sells)** suggest a **strong buying pressure** (1.7:1). This discrepancy may stem from a misinterpretation or typo in the ratio. Given the actual trade data, the **ratio is effectively >1.5**, aligning with the \"strong buying\" threshold in Rule 1.  \n- **Momentum**: Stable momentum confirms the market is not in a rapid upward or downward trend, supporting a conservative buy.  \n- **Price Change**: A +7.4% change is **low volatility**, which is ideal for entering a trade with a **market order (0%)**.  \n- **Volume**: Low volume (<$3k) implies limited liquidity, so **take-profit** and **stop-loss** ranges are narrower to manage risk.  \n\n---\n\n### **Parameters**  \n1. **Limit Order**: **0%** (Market order, as strong buying pressure dominates).  \n2. **Take Profit**: **+5% to +10%** (low volume, narrow range).  \n3. **Stop Loss**: **-5% to -8%** (low volatility, conservative risk).  \n4. **Time Frame**: **2h to 6h** (low volume suggests short-term holding).  \n\n---\n\n### **Final Output**  \n```plaintext\nDecision: BUY\nLimit Order: 0%\nTake Profit: 5% to 10%\nStop Loss: -5% to -8%\nTime Frame: 2h to 6h\n```",
      "trading_params": {
        "limit_order_price": 7.977440113510012e-05,
        "limit_order_pct": 0,
        "take_profit_price": 8.775184124861014e-05,
        "take_profit_pct": 10,
        "stop_loss_price": 7.578568107834511e-05,
        "stop_loss_pct": -5,
        "time_frame": "1h"
      }
    }
  ]
}