{
  "timestamp": "2026-01-26T10:40:16.009750",
  "scan_time": "20260126_104016",
  "total_tokens": 3,
  "buy_signals": 3,
  "watch_signals": 0,
  "skip_signals": 0,
  "tokens": [
    {
      "name": "Boggs / SOL",
      "mint": "9qv8phXG24opEDJvPijuftRTMfUTHuBHUZUSmKuzpump",
      "pool": "7Rc7QtLiAfscScbkFPhzUeTKnXMt2cL4NodDTCmvrq2a",
      "chart_url": "https://geckoterminal.com/solana/pools/7Rc7QtLiAfscScbkFPhzUeTKnXMt2cL4NodDTCmvrq2a",
      "decision": "BUY",
      "current_price": 3.465836670964828e-05,
      "volume": 11855.5523146691,
      "fdv": 34535.97868,
      "reserve": 17297.9891,
      "buys": 168,
      "sells": 168,
      "price_change": 25.294,
      "ai_reasoning": "**Reasoning:**  \n- **Buy/Sell Ratio (1.0):** Balanced, but recent trades show 163 sells vs. 137 buys (0.84 ratio). However, the overall ratio is 1.0, suggesting a potential reversal or consolidation.  \n- **Price Change (+25.3%):** Medium volatility \u2192 Limit at -2% (aggressive entry near market).  \n- **Volume ($11,856):** Medium \u2192 TP at +15% (balanced liquidity).  \n- **Momentum (STABLE):** Standard parameters with tighter SL (-10%) to account for potential dips.  \n- **Time Frame:** 4h for medium volatility and stable momentum.  \n\n**Note:** The recent sell dominance may indicate short-term weakness, but the balanced ratio and stable flow suggest a conservative BUY with dynamic parameters.",
      "trading_params": {
        "limit_order_price": 3.396519937545532e-05,
        "limit_order_pct": -2.0,
        "take_profit_price": 3.905997928177361e-05,
        "take_profit_pct": 15.0,
        "stop_loss_price": 3.0568679437909786e-05,
        "stop_loss_pct": -10.0,
        "time_frame": "4h"
      }
    },
    {
      "name": "quant / SOL",
      "mint": "3YeZGAcUgfLgAK7nxWMKyamLex8pGNSZUnCxmJijpump",
      "pool": "D152NMtWH8xa21owHRb4Mje8oy6GSaS5eCQjEzCNcbGT",
      "chart_url": "https://geckoterminal.com/solana/pools/D152NMtWH8xa21owHRb4Mje8oy6GSaS5eCQjEzCNcbGT",
      "decision": "BUY",
      "current_price": 0.00010333485449279474,
      "volume": 24840.9429710252,
      "fdv": 104816.5904,
      "reserve": 30676.1743,
      "buys": 829,
      "sells": 195,
      "price_change": 18.372,
      "ai_reasoning": "BUY | Limit:0% | TP:+15% | SL:-10% | Time:4h-1day",
      "trading_params": {
        "limit_order_price": 0.00010333485449279474,
        "limit_order_pct": 0.0,
        "take_profit_price": 0.00011883508266671394,
        "take_profit_pct": 15.0,
        "stop_loss_price": 9.300136904351527e-05,
        "stop_loss_pct": -10.0,
        "time_frame": "4h"
      }
    },
    {
      "name": "GOLDFISH / SOL",
      "mint": "9XSm7ShcXMkNxtY8bmhb1s5Jc33S4X3KTA8KkYAMpump",
      "pool": "4QjUpqmpdnRqr2xMi84J5ZBU84SJRfVZu9sLbVg6aYwp",
      "chart_url": "https://geckoterminal.com/solana/pools/4QjUpqmpdnRqr2xMi84J5ZBU84SJRfVZu9sLbVg6aYwp",
      "decision": "BUY",
      "current_price": 0.0002155893021907827,
      "volume": 10277.4030917652,
      "fdv": 216181.029,
      "reserve": 45587.8843,
      "buys": 78,
      "sells": 50,
      "price_change": 1.583,
      "ai_reasoning": "**Rationale:**  \n- **Buy/Sell Ratio (1.6):** Strong buying pressure (>1.5) triggers aggressive BUY parameters.  \n- **Price Change (+1.6%):** Low volatility (<10%), so Limit is 0% (market order).  \n- **Volume ($10,277):** High volume (> $10k) \u2192 TP +25% (mid-range of +20%\u2013+40%).  \n- **Momentum (STABLE):** Standard parameters with tighter SL (-5%) for low volatility.  \n- **Time Frame:** High volume suggests longer holding (4h\u20131d) to capitalize on liquidity.",
      "trading_params": {
        "limit_order_price": 0.0002155893021907827,
        "limit_order_pct": 0.0,
        "take_profit_price": 0.0002694866277384784,
        "take_profit_pct": 25.0,
        "stop_loss_price": 0.00020480983708124356,
        "stop_loss_pct": -5.0,
        "time_frame": "4h"
      }
    }
  ]
}