{
  "timestamp": "2026-02-16T08:16:55.660021",
  "scan_time": "20260216_081655",
  "total_tokens": 3,
  "buy_signals": 3,
  "watch_signals": 0,
  "skip_signals": 0,
  "tokens": [
    {
      "name": "DOZI / SOL",
      "mint": "9ZbpTmYLnQXsYk3MJWRnmr8Sfr4cArY5Ymwu7F6hpump",
      "pool": "8qjSrktZ6MZH1pdKFpk1iPnpHrQn47vWeyTyx7SWzCr7",
      "chart_url": "https://geckoterminal.com/solana/pools/8qjSrktZ6MZH1pdKFpk1iPnpHrQn47vWeyTyx7SWzCr7",
      "decision": "BUY",
      "current_price": 2.0226519477096778e-05,
      "volume": 17597.653603102,
      "fdv": 21237.38352,
      "reserve": 6737.3637,
      "buys": 141,
      "sells": 86,
      "price_change": 45.533,
      "ai_reasoning": "**Rationale:**  \n- **Buy/Sell Ratio (1.6):** Strong buying pressure (>1.5) triggers aggressive BUY with 0% limit (market order).  \n- **Price Change (+45.5%):** Medium volatility (10-50%), but strong buying momentum overrides volatility thresholds.  \n- **Volume ($17,598):** High volume (> $10k) justifies +30% TP for liquidity.  \n- **Stop Loss (-10%):** Medium volatility range (-8% to -15%) balances risk.  \n- **Time Frame (4h to 1day):** Strong trend (+45.5% price surge) aligns with extended holding periods.  \n\n**Key Factors:**  \n- Recent 5 trades (5 buys) and trade flow momentum (STABLE) confirm sustained buying pressure.  \n- High volume and recent buy dominance (65% in all thirds) validate aggressive entry.",
      "trading_params": {
        "limit_order_price": 2.0226519477096778e-05,
        "limit_order_pct": 0.0,
        "take_profit_price": 2.6294475320225812e-05,
        "take_profit_pct": 30.0,
        "stop_loss_price": 1.82038675293871e-05,
        "stop_loss_pct": -10.0,
        "time_frame": "4h"
      }
    },
    {
      "name": "Clawps / SOL",
      "mint": "FKPvoUKtnWwPi73SGLQrAux9DeP9RD8eGqrzcwynpump",
      "pool": "DsZMTVgfiiFr8XSiaMhX7BFBFLJaC87DcVYJjqG6EKzw",
      "chart_url": "https://geckoterminal.com/solana/pools/DsZMTVgfiiFr8XSiaMhX7BFBFLJaC87DcVYJjqG6EKzw",
      "decision": "BUY",
      "current_price": 2.5578847292247924e-05,
      "volume": 3096.0697910285,
      "fdv": 24641.31294,
      "reserve": 12087.2129,
      "buys": 48,
      "sells": 43,
      "price_change": 34.34,
      "ai_reasoning": "**Rationale:**  \n- **Buy/Sell Ratio (1.1):** Balanced, but recent trades (57% buy ratio) and stable flow momentum suggest conservative buying.  \n- **Volatility (34.3% price change):** Medium volatility \u2192 Limit at -3% (mid-range of -2% to -5%).  \n- **Volume ($3,096):** Low volume \u2192 Take profit at +6% (mid-range of +5% to +10%).  \n- **Stop Loss:** Medium volatility \u2192 -9% (mid-range of -8% to -15%).  \n- **Time Frame:** Low volume + stable momentum \u2192 3h (mid-range of 2h to 6h).  \n- **Decision:** Aggressive conservative buy due to strong recent buying pressure and stable flow.",
      "trading_params": {
        "limit_order_price": 2.4811481873480486e-05,
        "limit_order_pct": -3.0,
        "take_profit_price": 2.6300170785889316e-05,
        "take_profit_pct": 6.0,
        "stop_loss_price": 2.2578448504867244e-05,
        "stop_loss_pct": -9.0,
        "time_frame": "3h"
      }
    },
    {
      "name": "TrollPunch / SOL",
      "mint": "5jBTtBmmnWQLXSeLVRdXZWGSv6As7Z8hDR4vxK8kpump",
      "pool": "H4ExC887HUPCMJmR5YtJi9dTkaMnZWP9ecmKp6qmbRSE",
      "chart_url": "https://geckoterminal.com/solana/pools/H4ExC887HUPCMJmR5YtJi9dTkaMnZWP9ecmKp6qmbRSE",
      "decision": "BUY",
      "current_price": 1.4286008619260021e-05,
      "volume": 2519.8224644073,
      "fdv": 14435.68041,
      "reserve": 5949.7523,
      "buys": 34,
      "sells": 11,
      "price_change": 21.336,
      "ai_reasoning": "**Reasoning**:  \n- **Buy/Sell Ratio (3.1)**: Strong buying pressure (>1.5) with stable momentum \u2192 Aggressive entry (0% limit).  \n- **Price Change (+21.3%)**: Medium volatility \u2192 TP at +7% (low volume range) and SL at -10% (medium volatility range).  \n- **Volume ($2,520)**: Low volume \u2192 Shorter time frame (2h to 6h) and tighter TP/SL.  \n- **Trade Flow**: Balanced buy dominance across all thirds (72-68% buys) confirms strong institutional buying.  \n- **Recent Trades**: 207 buys vs. 93 sells (ratio 3.1) and 3 buys in last 5 trades \u2192 Confirms sustained bullish momentum.",
      "trading_params": {
        "limit_order_price": 1.4286008619260021e-05,
        "limit_order_pct": 0.0,
        "take_profit_price": 1.5286029222608222e-05,
        "take_profit_pct": 7.0,
        "stop_loss_price": 1.2857407757334019e-05,
        "stop_loss_pct": -10.0,
        "time_frame": "2h"
      }
    }
  ]
}