{
  "timestamp": "2026-01-16T15:46:53.732578",
  "scan_time": "20260116_154653",
  "total_tokens": 3,
  "buy_signals": 3,
  "watch_signals": 0,
  "skip_signals": 0,
  "tokens": [
    {
      "name": "SilPsyop / SOL",
      "mint": "4Q6J5BXzaTqg7Ab2P7JHJNDE9vUra7m231frW8kHpump",
      "pool": "2hBVuYawYmdbxQbZ2hytM8pYmAGSH5TyNnxY44McSMf8",
      "chart_url": "https://geckoterminal.com/solana/pools/2hBVuYawYmdbxQbZ2hytM8pYmAGSH5TyNnxY44McSMf8",
      "decision": "BUY",
      "current_price": 3.37998663947598e-05,
      "volume": 10011.8714358673,
      "fdv": 34857.82594,
      "reserve": 11051.9607,
      "buys": 54,
      "sells": 36,
      "price_change": -11.767,
      "ai_reasoning": "**Rationale:**  \n- **Buy/Sell Ratio (1.5):** Strong buying pressure triggers aggressive entry (0% limit).  \n- **Price Change (-11.8%):** Medium volatility (10-50% range) \u2192 -2% to -5% limit, but strong buying overrides this.  \n- **Volume ($10,012):** High volume \u2192 +20% to +40% TP, but adjusted to +25% for balance.  \n- **Momentum (STABLE):** Standard parameters apply, but strong buying amplifies TP.  \n- **Stop Loss:** Medium volatility (-8% to -15%) \u2192 -10% for tighter risk.  \n- **Time Frame:** High volume + stable momentum \u2192 4h for medium-term holding.",
      "trading_params": {
        "limit_order_price": 3.37998663947598e-05,
        "limit_order_pct": 0.0,
        "take_profit_price": 4.224983299344975e-05,
        "take_profit_pct": 25.0,
        "stop_loss_price": 3.041987975528382e-05,
        "stop_loss_pct": -10.0,
        "time_frame": "4h"
      }
    },
    {
      "name": "BLINKZ / SOL",
      "mint": "2x916Dehzgt8tGAickj26JT6nFfthWcVdksHiLaJpump",
      "pool": "EyrvfhXuK3o1p1ydCu4DLVyzL7Jm6qgUw9bzeV59qVuE",
      "chart_url": "https://geckoterminal.com/solana/pools/EyrvfhXuK3o1p1ydCu4DLVyzL7Jm6qgUw9bzeV59qVuE",
      "decision": "BUY",
      "current_price": 0.00012638229368734942,
      "volume": 5456.9107037941,
      "fdv": 126382.2937,
      "reserve": 34948.1088,
      "buys": 23,
      "sells": 31,
      "price_change": -5.599,
      "ai_reasoning": "WATCH (Recent sell dominance with emerging buy momentum, but ratio <1.0 indicates caution)  \nBUY | Limit:-0% | TP:+10% | SL:-8% | Time:4h  \n\n**Rationale:**  \n- **Buy/Sell Ratio (0.7):** Sells dominate, but recent 5 trades show 4 buys (80% buy dominance) suggesting potential reversal.  \n- **Volatility (-5.6%):** Low volatility \u2192 **Limit: 0% (market order)** to avoid waiting for dips.  \n- **Volume ($5,457):** Low volume \u2192 **TP: +10%** (aggressive take profit for limited liquidity).  \n- **Stop Loss:** Low volatility \u2192 **SL: -8%** (tight stop to preserve capital).  \n- **Time Frame:** Stable momentum + low volume \u2192 **4h** for balanced risk/reward.  \n\n**Key Signal:** While the ratio is below 1.0, the recent trade flow (43% buys in last 100 trades) and last 5 trades (4 buys) suggest a possible reversal. However, the overall sell pressure remains high, warranting a **WATCH** with aggressive parameters to capitalize on potential momentum shifts.",
      "trading_params": {
        "limit_order_price": 0.00012638229368734942,
        "limit_order_pct": -0.0,
        "take_profit_price": 0.00013902052305608437,
        "take_profit_pct": 10.0,
        "stop_loss_price": 0.00011627171019236147,
        "stop_loss_pct": -8.0,
        "time_frame": "4h"
      }
    },
    {
      "name": "PsyCartoon / SOL",
      "mint": "DAAXmRU9KUEuyqF8VuddbcL5X4QhQ3tTDMYxDbNgpump",
      "pool": "5aS1BeY8dMUwjXkMjjG217hwR7etgXCkyc9pBiUr5GUK",
      "chart_url": "https://geckoterminal.com/solana/pools/5aS1BeY8dMUwjXkMjjG217hwR7etgXCkyc9pBiUr5GUK",
      "decision": "BUY",
      "current_price": 0.00018385096357501985,
      "volume": 3856.8709415585,
      "fdv": 183850.9636,
      "reserve": 48435.2616,
      "buys": 15,
      "sells": 11,
      "price_change": -8.477,
      "ai_reasoning": "**Decision:**  \nThe provided data indicates a **balanced Buy/Sell Ratio (1.4)**, suggesting a **conservative BUY** opportunity. However, the recent trades (123 buys vs. 177 sells) and trade flow dynamics (stable momentum) imply a **cautious approach**.  \n\n**Dynamic Parameters:**  \n- **Limit Order:** Medium volatility (-8.5% price change) \u2192 **-2%** (to capture pullbacks).  \n- **Take Profit:** Medium volume ($3,857) \u2192 **+15%** (mid-range target).  \n- **Stop Loss:** Medium volatility \u2192 **-8%** (to limit downside risk).  \n- **Time Frame:** Medium volatility \u2192 **2 hours** (short-term holding period).  \n\n**Final Output:**  \n**BUY | Limit:-2% | TP:+15% | SL:-8% | Time:2h**  \n\nThis strategy balances risk and reward while aligning with the observed market dynamics.",
      "trading_params": {
        "limit_order_price": 0.00018017394430351944,
        "limit_order_pct": -2.0,
        "take_profit_price": 0.00020720003594904734,
        "take_profit_pct": 15.0,
        "stop_loss_price": 0.0001657600287592379,
        "stop_loss_pct": -8.0,
        "time_frame": "2h"
      }
    }
  ]
}